apphub_client/__init__.py
apphub_client/api_client.py
apphub_client/api_response.py
apphub_client/configuration.py
apphub_client/exceptions.py
apphub_client/py.typed
apphub_client/rest.py
apphub_client/api/__init__.py
apphub_client/api/apphub_api.py
apphub_client/models/__init__.py
apphub_client/models/apphub_v1_environment.py
apphub_client/models/apphub_v1_environment_list.py
apphub_client/models/apphub_v1_environment_spec.py
apphub_client/models/apphub_v1_environment_spec_builder.py
apphub_client/models/apphub_v1_environment_spec_builder_container.py
apphub_client/models/apphub_v1_environment_spec_builder_container_env_from_inner.py
apphub_client/models/apphub_v1_environment_spec_builder_container_env_from_inner_config_map_ref.py
apphub_client/models/apphub_v1_environment_spec_builder_container_env_from_inner_secret_ref.py
apphub_client/models/apphub_v1_environment_spec_builder_container_env_inner.py
apphub_client/models/apphub_v1_environment_spec_builder_container_env_inner_value_from.py
apphub_client/models/apphub_v1_environment_spec_builder_container_env_inner_value_from_config_map_key_ref.py
apphub_client/models/apphub_v1_environment_spec_builder_container_env_inner_value_from_field_ref.py
apphub_client/models/apphub_v1_environment_spec_builder_container_env_inner_value_from_resource_field_ref.py
apphub_client/models/apphub_v1_environment_spec_builder_container_env_inner_value_from_secret_key_ref.py
apphub_client/models/apphub_v1_environment_spec_builder_container_lifecycle.py
apphub_client/models/apphub_v1_environment_spec_builder_container_lifecycle_post_start.py
apphub_client/models/apphub_v1_environment_spec_builder_container_lifecycle_post_start_exec.py
apphub_client/models/apphub_v1_environment_spec_builder_container_lifecycle_post_start_http_get.py
apphub_client/models/apphub_v1_environment_spec_builder_container_lifecycle_post_start_http_get_http_headers_inner.py
apphub_client-1.0.6.dist-info/METADATA
apphub_client-1.0.6.dist-info/WHEEL
apphub_client-1.0.6.dist-info/top_level.txt
apphub_client-1.0.6.dist-info/RECORD
